setup.py
distributions_pyprojects/Binomialdistribution.py
distributions_pyprojects/Gaussiandistribution.py
distributions_pyprojects/Generaldistribution.py
distributions_pyprojects/__init__.py
distributions_pyprojects.egg-info/PKG-INFO
distributions_pyprojects.egg-info/SOURCES.txt
distributions_pyprojects.egg-info/dependency_links.txt
distributions_pyprojects.egg-info/not-zip-safe
distributions_pyprojects.egg-info/top_level.txt