Metadata-Version: 1.0
Name: distributions-pyprojects
Version: 0.1
Summary: Gaussian and Binomial distributions_pyprojects
Home-page: UNKNOWN
Author: Lily Ng
Author-email: lilyng15@outlook.com
License: UNKNOWN
Platform: UNKNOWN
